<?xml version="1.0" encoding="UTF-8"?>
<openerp>
    <data>
    	
    	<!-- Product product cost concept form view -->
    	<record model="ir.ui.view" id="product_product_cost_concept_form_view">
			<field name="name">product.product.cost.concept.form</field>
			<field name="model">product.product.cost.concept</field>
			<field name="type">form</field>
			<field name="arch" type="xml">
				<form string="Product cost concept">
					<field name="name" select="1"/>
				</form>
			</field>
		</record>
		
		<!-- Product product cost concept tree view -->
		<record model="ir.ui.view" id="product_product_cost_concept_tree_view">
			<field name="name">product.product.cost.concept.tree</field>
            <field name="model">product.product.cost.concept</field>
            <field name="type">tree</field>
            <field name="arch" type="xml">
            	<tree string="Product cost concepts">
                	<field name="name"/>
                </tree>
            </field>
        </record>
        
        <!-- Product cost concept tree view action -->
        <record model="ir.actions.act_window" id="action_product_product_cost_concept_tree_view">
			<field name="name">Product cost concepts</field>
    		<field name="type">ir.actions.act_window</field>
        	<field name="res_model">product.product.cost.concept</field>
        	<field name="view_type">form</field>
        	<field name="view_mode">tree,form</field>
        	<field name="view_id" ref="product_product_cost_concept_tree_view"/>
    	</record>
    	
    	<!-- Product cost concept tree view action menuitem -->
    	<menuitem id="product_product_cost_concept_tree_menu" name="Additional product cost concepts" parent="product.prod_config_main" sequence= "35" action="action_product_product_cost_concept_tree_view"/>



		<!-- product category cost concept form view -->
		<record model="ir.ui.view" id="product_category_cost_concept_form_view">
			<field name="name">product.category.cost.concept.form</field>
			<field name="model">product.category.cost.concept</field>
			<field name="type">form</field>
			<field name="arch" type="xml">
				<form string="Product category - Additional cost concept">
					<field name="name" select="1"/>
				</form>
			</field>
		</record>
		
		<!-- product category cost concept tree view -->
		<record model="ir.ui.view" id="product_category_cost_concept_tree_view">
			<field name="name">product.category.cost.concept.tree</field>
            <field name="model">product.category.cost.concept</field>
            <field name="type">tree</field>
            <field name="arch" type="xml">
            	<tree string="Product category - Additional cost concepts">
                	<field name="name"/>
                </tree>
            </field>
        </record>




		<!-- product category form view -->
    	<record id="product_category_form_view" model="ir.ui.view">
            <field name="name">product.category.form.mrp_costing</field>
            <field name="model">product.category</field>
            <field name="type">form</field>
            <field name="inherit_id" ref="product.product_category_form_view"/>
            <field name="priority" eval="17"/>
            <field name="arch" type="xml">
            	<xpath expr="//group[@name='parent']/.." position="after">
            		<group name="cost_concepts" string="Cost concepts">
            			<field name="cost_concept_ids" colspan="4" nolabel="1" widget="one2many_list" height="400"/>
            			<!-- # TODO: Button 'Import concepts' -->
            		</group>
            	</xpath>
            </field>
        </record>
    	
    	
    	
    	
    	<!-- product cost item form view -->
		<record model="ir.ui.view" id="product_product_cost_item_form_view">
			<field name="name">product.product.cost.item.form</field>
			<field name="model">product.product.cost.item</field>
			<field name="type">form</field>
			<field name="arch" type="xml">
				<form string="Product - Additional cost item">
					<field name="name" select="1"/>
					<field name="cost"/>
				</form>
			</field>
		</record>
		
		<!-- product cost item tree view -->
		<record model="ir.ui.view" id="product_product_cost_item_tree_view">
			<field name="name">product.product.cost.item.tree</field>
            <field name="model">product.product.cost.item</field>
            <field name="type">tree</field>
            <field name="arch" type="xml">
            	<tree string="Additional costs">
                	<field name="name"/>
                	<field name="cost"/>
                </tree>
            </field>
        </record>
    	
    	
    	
    	
    	<!-- product form view -->
    	<record id="product_product_form_view" model="ir.ui.view">
            <field name="name">product_product_form_view_mrp_costing</field>
            <field name="model">product.product</field>
            <field name="type">form</field>
            <field name="inherit_id" ref="product.product_normal_form_view"/>
            <field name="priority" eval="17"/>
            <field name="arch" type="xml">
            
            	<!-- hide some fields defined on stock_account -->
            	<!--<field name="standard_price" position="replace"/>-->
            	<!--<field name="cost_method" position="replace"/>-->
            	<!--<xpath expr="//label[@string='Cost Price']" position="replace"/>-->
       			<!--<xpath expr="//separator[@string='Inventory Valuation']/.." position="replace"/>-->
            	
            	<xpath expr="//notebook/page[last()]" position="after">
            		<page string="Costing">
            			<group name="costs">
	            			<group name="base_costs">
	            				<separator string="Base costs" colspan="4"/>
	            				<field name="material_cost" attrs="{'invisible': [('bom_count','=',0)]}"/>
	            				<field name="production_cost" attrs="{'invisible': [('bom_count','=',0)]}"/>
	            				<field name="other_concepts_cost"/>
	            				<separator string="" colspan="4"/>
	            				<field name="computed_cost"/>
		                        <field name="standard_price" attrs="{'readonly':['|','&amp;', ('valuation','=','real_time'), ('cost_method', 'in', ['standard', 'average']),('cost_method', '=', 'auto_mpa')]}"/>
		                        <button name="%(stock_account.action_view_change_standard_price)d" string="- update"
		                            type="action" attrs="{'invisible':['|', ('valuation','!=', 'real_time'), ('cost_method', 'not in', ['standard', 'average', 'auto_mpa'])]}"
		                            class="oe_link" groups="stock_account.group_inventory_valuation"/>
		            		</group>
		            		<group name="cost_details">
		            			<separator string="Additional cost details" colspan="4"/>
		            			<field name="concept_cost_ids" nolabel="1" widget="one2many_list" height="400" colspan="4"/>
		            			<button name="default_cost_concepts" string="Clear and import concepts" type="object" class="oe_link" colspan="4"/>
		            		</group>
            			</group>
            			<group>
            				<separator string="Costing method" colspan="4"/>
            				<field name="cost_method" attrs="{'invisible': [('type','=','service')]}"/>
            			</group>
	                    <group groups="stock_account.group_inventory_valuation" attrs="{'invisible': [('type','=','service')]}">
	                        <separator string="Inventory Valuation" colspan="4"/>
	                        <group colspan="2" col="2">
	                            <field name="valuation" attrs="{'readonly':[('type', '=', 'service')]}"/>
	                        </group>
	                        <group colspan="2" col="2">
	                            <field name="property_stock_account_input" attrs="{'invisible':[('valuation', '!=', 'real_time')]}"
	                                domain="[('type','&lt;&gt;','view'),('type','&lt;&gt;','consolidation')]"/>
	                            <field name="property_stock_account_output" attrs="{'invisible':[('valuation', '!=', 'real_time')]}"
	                                domain="[('type','&lt;&gt;','view'),('type','&lt;&gt;','consolidation')]"/>
	                        </group>
	                    </group>
	                    <newline/>

            			
            			
            			
            		</page>
            	</xpath>

            </field>
        </record>
        
        <!-- <record id="product_product_tree_view" model="ir.ui.view">
            <field name="name">product.product.product.tree.mrp_costing</field>
            <field name="model">product.product</field>
            <field name="inherit_id" ref="product.product_tree_view"/>
			<field name="priority" eval="17"/>
            <field name="arch" type="xml">
            	<field name="uom_id" position="after">
            		<field name="material_cost" invisible="1"/>
            		<field name="standard_price"/>
            	</field>
            </field>
        </record> -->

		<record id="product_product_kanban_view" model="ir.ui.view">
            <field name="name">Product.product.product.kanban.mrp_costing</field>
            <field name="model">product.product</field>
            <field name="inherit_id" ref="product.product_kanban_view"/>
            <field name="arch" type="xml">
            	<field name="name" position="after">
	            	<field name="material_cost" invisible="1"/>
	            	<field name="computed_cost" invisible="1"/>
            	</field>
            </field>
        </record>
    	
    	
    	
    	
    </data>
</openerp>